wbi/__init__.py
wbi/__main__.py
wbi/_version.py
wbi/alignment.py
wbi/config.yaml
wbi/configuration.py
wbi/dat.py
wbi/experiment.py
wbi/file.py
wbi/hires.py
wbi/timing.py
wbi/commands/__init__.py
wbi/commands/align.py
wbi/commands/centerline.py
wbi/commands/flash_finder.py
wbi/commands/remote.py
wbi/data/__init__.py
wbi/data/eigenWorms.mat
wbi/data/ondemand.py
wbi/legacy/__init__.py
wbi/legacy/flash_finder.py
wbi/legacy/make_centerline.py
wbi/legacy/cline/__init__.py
wbi/legacy/cline/centerline_funcs.py
wbi/legacy/cline/plot_cline.py
wbi/legacy/cline/unet_segmentation/__init__.py
wbi/legacy/cline/unet_segmentation/data_augmentation.py
wbi/legacy/cline/unet_segmentation/load_data.py
wbi/legacy/cline/unet_segmentation/train.py
wbi/legacy/cline/unet_segmentation/unet_model.py
wbi/legacy/cline/unet_segmentation/utils.py
wbi/matlab/__init__.py
wbi/matlab/imresize.py
wbi/matlab/misc.py
wbi/remote/__init__.py
wbi/remote/remote.py
wbi/remote/templates/__init__.py
wbi/remote/templates/hello.jinja
wbi/remote/templates/pyhello.jinja
wbi/remote/templates/ray.jinja
wbi/ui/QtImageStackViewer.py
wbi/ui/QtImageViewer.py
wbi/ui/__init__.py
wbi/ui/image_align.py
leiferlab_wbi-0.2.3.dist-info/METADATA
leiferlab_wbi-0.2.3.dist-info/WHEEL
leiferlab_wbi-0.2.3.dist-info/entry_points.txt
leiferlab_wbi-0.2.3.dist-info/top_level.txt
leiferlab_wbi-0.2.3.dist-info/RECORD
